pycerberus/__init__.py
pycerberus/api.py
pycerberus/compat.py
pycerberus/error_conversion.py
pycerberus/errors.py
pycerberus/i18n.py
pycerberus/release.py
pycerberus/schema.py
pycerberus/schemas.py
pycerberus/test_util.py
pycerberus/lib/__init__.py
pycerberus/lib/attribute_dict.py
pycerberus/lib/form_data.py
pycerberus/lib/tests/__init__.py
pycerberus/lib/tests/field_data_test.py
pycerberus/lib/tests/form_data_test.py
pycerberus/lib/tests/repeating_field_data_test.py
pycerberus/locales/__init__.py
pycerberus/locales/pycerberus.pot
pycerberus/locales/de/__init__.py
pycerberus/locales/de/LC_MESSAGES/pycerberus.mo
pycerberus/locales/de/LC_MESSAGES/pycerberus.po
pycerberus/validators/__init__.py
pycerberus/validators/basic_numbers.py
pycerberus/validators/checkbox.py
pycerberus/validators/domain.py
pycerberus/validators/email.py
pycerberus/validators/foreach.py
pycerberus/validators/matching_fields.py
pycerberus/validators/oneof.py
pycerberus/validators/regex.py
pycerberus/validators/string.py
pycerberus-0.7.1.dist-info/LICENSE.txt
pycerberus-0.7.1.dist-info/METADATA
pycerberus-0.7.1.dist-info/WHEEL
pycerberus-0.7.1.dist-info/top_level.txt
pycerberus-0.7.1.dist-info/RECORD
