Metadata-Version: 2.1
Name: pycerberus
Version: 0.7.1
Summary: Highly flexible input validation library
Home-page: https://github.com/FelixSchwarz/pycerberus
Author: Felix Schwarz
Author-email: felix.schwarz@oss.schwarz.eu
License: MIT
Project-URL: Source Code, https://github.com/FelixSchwarz/pycerberus
Project-URL: Bug Tracker, https://github.com/FelixSchwarz/pycerberus/issues
Project-URL: Documentation, https://pycerberus.readthedocs.io
Platform: UNKNOWN
Classifier: Development Status :: 4 - Beta
Classifier: Intended Audience :: Developers
Classifier: License :: OSI Approved :: MIT License
Classifier: Operating System :: OS Independent
Classifier: Programming Language :: Python
Classifier: Programming Language :: Python :: 3
Classifier: Topic :: Software Development :: Libraries :: Python Modules
License-File: LICENSE.txt
Requires-Dist: six
Requires-Dist: importlib-resources ; python_version < "3.9"
Provides-Extra: i18n
Requires-Dist: Babel (>=0.9.5) ; extra == 'i18n'
Provides-Extra: testing
Requires-Dist: Babel (>=0.9.5) ; extra == 'testing'
Requires-Dist: PythonicTestcase (>=1.1.0) ; extra == 'testing'
Requires-Dist: pytest ; extra == 'testing'
